neo_python_sdk/__init__.py
neo_python_sdk/npq_client.py
neo_python_sdk-1.16.1.dist-info/LICENSE.txt
neo_python_sdk-1.16.1.dist-info/METADATA
neo_python_sdk-1.16.1.dist-info/WHEEL
neo_python_sdk-1.16.1.dist-info/top_level.txt
neo_python_sdk-1.16.1.dist-info/RECORD
