Metadata-Version: 2.1
Name: neo-python-sdk
Version: 1.16.1
Summary: Neo SDK for Python with some additional libraries to support the development of Neo Sentinels (NSX).
Home-page: https://github.com/neohelden/neo_python_sdk
Author: Jan-Eric Gaidusch <Neohelden GmbH>
License: apache-2.0
Keywords: neohelden,neo,neo-sdk
Platform: UNKNOWN
Classifier: Development Status :: 3 - Alpha
Classifier: Intended Audience :: Developers
Classifier: Topic :: Software Development :: Build Tools
Classifier: License :: OSI Approved :: Apache Software License
Classifier: Programming Language :: Python :: 3.5
Classifier: Programming Language :: Python :: 3.6
Classifier: Programming Language :: Python :: 3.7
Classifier: Programming Language :: Python :: 3.8
Classifier: Programming Language :: Python :: 3.9
Requires-Python: >=3.5
Requires-Dist: asyncio-nats-client (==0.11.4)
Requires-Dist: asyncio (==3.4.3)
Requires-Dist: sentry-sdk (==1.0.0)
